kaemo_client/__init__.py
kaemo_client/api_client.py
kaemo_client/configuration.py
kaemo_client/rest.py
kaemo_client/apis/__init__.py
kaemo_client/apis/accesses_api.py
kaemo_client/apis/actors_api.py
kaemo_client/apis/address_api.py
kaemo_client/apis/attributes_api.py
kaemo_client/apis/blog_categories_api.py
kaemo_client/apis/blog_pages_api.py
kaemo_client/apis/bookmarks_api.py
kaemo_client/apis/cart_rules_api.py
kaemo_client/apis/carts_api.py
kaemo_client/apis/categories_api.py
kaemo_client/apis/cms_categories_api.py
kaemo_client/apis/cms_pages_api.py
kaemo_client/apis/countries_api.py
kaemo_client/apis/currencies_api.py
kaemo_client/apis/customer_threads_api.py
kaemo_client/apis/customers_api.py
kaemo_client/apis/directors_api.py
kaemo_client/apis/extracts_api.py
kaemo_client/apis/facebook_api.py
kaemo_client/apis/feature_values_api.py
kaemo_client/apis/features_api.py
kaemo_client/apis/genders_api.py
kaemo_client/apis/geolocations_api.py
kaemo_client/apis/groups_api.py
kaemo_client/apis/images_api.py
kaemo_client/apis/languages_api.py
kaemo_client/apis/manufacturers_api.py
kaemo_client/apis/media_files_api.py
kaemo_client/apis/media_sources_api.py
kaemo_client/apis/o_auth_api.py
kaemo_client/apis/order_histories_api.py
kaemo_client/apis/order_states_api.py
kaemo_client/apis/orders_api.py
kaemo_client/apis/payment_modules_api.py
kaemo_client/apis/player_api.py
kaemo_client/apis/product_accesses_api.py
kaemo_client/apis/products_api.py
kaemo_client/apis/stats_api.py
kaemo_client/apis/subscriptions_api.py
kaemo_client/apis/subtitles_api.py
kaemo_client/apis/suppliers_api.py
kaemo_client/apis/tasks_api.py
kaemo_client/apis/videos_api.py
kaemo_client/apis/widgets_api.py
kaemo_client/models/__init__.py
kaemo_client/models/actor.py
kaemo_client/models/actors.py
kaemo_client/models/address.py
kaemo_client/models/blog_category.py
kaemo_client/models/blog_category_lists.py
kaemo_client/models/blog_page.py
kaemo_client/models/blog_page_lists.py
kaemo_client/models/cart.py
kinow_client-1.0.0.dist-info/LICENSE
kinow_client-1.0.0.dist-info/METADATA
kinow_client-1.0.0.dist-info/WHEEL
kinow_client-1.0.0.dist-info/top_level.txt
kinow_client-1.0.0.dist-info/RECORD
